{
	"inputs" : 
	[
		{
			"path" : "CMakeLists.txt"
		},
		{
			"isGenerated" : true,
			"path" : "build/CMakeFiles/3.29.2/CMakeSystem.cmake"
		},
		{
			"isCMake" : true,
			"isExternal" : true,
			"path" : "/usr/share/cmake-3.29/Modules/CMakeSystemSpecificInitialize.cmake"
		},
		{
			"isCMake" : true,
			"isExternal" : true,
			"path" : "/usr/share/cmake-3.29/Modules/Platform/Linux-Initialize.cmake"
		},
		{
			"isGenerated" : true,
			"path" : "build/CMakeFiles/3.29.2/CMakeCCompiler.cmake"
		},
		{
			"isGenerated" : true,
			"path" : "build/CMakeFiles/3.29.2/CMakeCXXCompiler.cmake"
		},
		{
			"isCMake" : true,
			"isExternal" : true,
			"path" : "/usr/share/cmake-3.29/Modules/CMakeSystemSpecificInformation.cmake"
		},
		{
			"isCMake" : true,
			"isExternal" : true,
			"path" : "/usr/share/cmake-3.29/Modules/CMakeGenericSystem.cmake"
		},
		{
			"isCMake" : true,
			"isExternal" : true,
			"path" : "/usr/share/cmake-3.29/Modules/CMakeInitializeConfigs.cmake"
		},
		{
			"isCMake" : true,
			"isExternal" : true,
			"path" : "/usr/share/cmake-3.29/Modules/Platform/Linux.cmake"
		},
		{
			"isCMake" : true,
			"isExternal" : true,
			"path" : "/usr/share/cmake-3.29/Modules/Platform/UnixPaths.cmake"
		},
		{
			"isCMake" : true,
			"isExternal" : true,
			"path" : "/usr/share/cmake-3.29/Modules/CMakeCInformation.cmake"
		},
		{
			"isCMake" : true,
			"isExternal" : true,
			"path" : "/usr/share/cmake-3.29/Modules/CMakeLanguageInformation.cmake"
		},
		{
			"isCMake" : true,
			"isExternal" : true,
			"path" : "/usr/share/cmake-3.29/Modules/Compiler/GNU-C.cmake"
		},
		{
			"isCMake" : true,
			"isExternal" : true,
			"path" : "/usr/share/cmake-3.29/Modules/Compiler/GNU.cmake"
		},
		{
			"isCMake" : true,
			"isExternal" : true,
			"path" : "/usr/share/cmake-3.29/Modules/Compiler/CMakeCommonCompilerMacros.cmake"
		},
		{
			"isCMake" : true,
			"isExternal" : true,
			"path" : "/usr/share/cmake-3.29/Modules/Platform/Linux-GNU-C.cmake"
		},
		{
			"isCMake" : true,
			"isExternal" : true,
			"path" : "/usr/share/cmake-3.29/Modules/Platform/Linux-GNU.cmake"
		},
		{
			"isCMake" : true,
			"isExternal" : true,
			"path" : "/usr/share/cmake-3.29/Modules/CMakeCommonLanguageInclude.cmake"
		},
		{
			"isCMake" : true,
			"isExternal" : true,
			"path" : "/usr/share/cmake-3.29/Modules/CMakeCXXInformation.cmake"
		},
		{
			"isCMake" : true,
			"isExternal" : true,
			"path" : "/usr/share/cmake-3.29/Modules/CMakeLanguageInformation.cmake"
		},
		{
			"isCMake" : true,
			"isExternal" : true,
			"path" : "/usr/share/cmake-3.29/Modules/Compiler/GNU-CXX.cmake"
		},
		{
			"isCMake" : true,
			"isExternal" : true,
			"path" : "/usr/share/cmake-3.29/Modules/Compiler/GNU.cmake"
		},
		{
			"isCMake" : true,
			"isExternal" : true,
			"path" : "/usr/share/cmake-3.29/Modules/Platform/Linux-GNU-CXX.cmake"
		},
		{
			"isCMake" : true,
			"isExternal" : true,
			"path" : "/usr/share/cmake-3.29/Modules/Platform/Linux-GNU.cmake"
		},
		{
			"isCMake" : true,
			"isExternal" : true,
			"path" : "/usr/share/cmake-3.29/Modules/CMakeCommonLanguageInclude.cmake"
		},
		{
			"path" : "cmake/external_packages.cmake"
		},
		{
			"path" : "cmake/CPM.cmake"
		},
		{
			"isCMake" : true,
			"isExternal" : true,
			"path" : "/usr/share/cmake-3.29/Modules/FetchContent.cmake"
		},
		{
			"isCMake" : true,
			"isExternal" : true,
			"path" : "/usr/share/cmake-3.29/Modules/ExternalProject/shared_internal_commands.cmake"
		},
		{
			"isCMake" : true,
			"isExternal" : true,
			"path" : "/usr/share/cmake-3.29/Modules/FindVulkan.cmake"
		},
		{
			"isCMake" : true,
			"isExternal" : true,
			"path" : "/usr/share/cmake-3.29/Modules/FindPackageHandleStandardArgs.cmake"
		},
		{
			"isCMake" : true,
			"isExternal" : true,
			"path" : "/usr/share/cmake-3.29/Modules/FindPackageMessage.cmake"
		},
		{
			"isExternal" : true,
			"path" : "/usr/lib/x86_64-linux-gnu/cmake/glfw3/glfw3ConfigVersion.cmake"
		},
		{
			"isExternal" : true,
			"path" : "/usr/lib/x86_64-linux-gnu/cmake/glfw3/glfw3Config.cmake"
		},
		{
			"isExternal" : true,
			"path" : "/usr/lib/x86_64-linux-gnu/cmake/glfw3/glfw3Targets.cmake"
		},
		{
			"isExternal" : true,
			"path" : "/usr/lib/x86_64-linux-gnu/cmake/glfw3/glfw3Targets-none.cmake"
		},
		{
			"isExternal" : true,
			"path" : "/usr/lib/cmake/glm/glmConfig-version.cmake"
		},
		{
			"isExternal" : true,
			"path" : "/usr/lib/cmake/glm/glmConfig.cmake"
		},
		{
			"isExternal" : true,
			"path" : "/usr/local/lib/cmake/ktx/KtxConfigVersion.cmake"
		},
		{
			"isExternal" : true,
			"path" : "/usr/local/lib/cmake/ktx/KtxConfig.cmake"
		},
		{
			"isExternal" : true,
			"path" : "/usr/local/lib/cmake/ktx/KtxTargets.cmake"
		},
		{
			"isExternal" : true,
			"path" : "/usr/local/lib/cmake/ktx/KtxTargets-release.cmake"
		},
		{
			"isCMake" : true,
			"isExternal" : true,
			"path" : "/usr/share/cmake-3.29/Modules/FindGit.cmake"
		},
		{
			"isCMake" : true,
			"isExternal" : true,
			"path" : "/usr/share/cmake-3.29/Modules/FindPackageHandleStandardArgs.cmake"
		},
		{
			"isCMake" : true,
			"isExternal" : true,
			"path" : "/usr/share/cmake-3.29/Modules/FindPackageMessage.cmake"
		},
		{
			"isCMake" : true,
			"isExternal" : true,
			"path" : "/usr/share/cmake-3.29/Modules/FetchContent/CMakeLists.cmake.in"
		},
		{
			"isGenerated" : true,
			"path" : "build/install/lib/cmake/imgui/imguiConfigVersion.cmake"
		},
		{
			"isGenerated" : true,
			"path" : "build/install/lib/cmake/imgui/imguiConfig.cmake"
		},
		{
			"isCMake" : true,
			"isExternal" : true,
			"path" : "/usr/share/cmake-3.29/Modules/CMakeFindDependencyMacro.cmake"
		},
		{
			"isCMake" : true,
			"isExternal" : true,
			"path" : "/usr/share/cmake-3.29/Modules/FindVulkan.cmake"
		},
		{
			"isCMake" : true,
			"isExternal" : true,
			"path" : "/usr/share/cmake-3.29/Modules/FindPackageHandleStandardArgs.cmake"
		},
		{
			"isCMake" : true,
			"isExternal" : true,
			"path" : "/usr/share/cmake-3.29/Modules/FindPackageMessage.cmake"
		},
		{
			"isGenerated" : true,
			"path" : "build/install/lib/cmake/imgui/imguiTargets.cmake"
		},
		{
			"isGenerated" : true,
			"path" : "build/install/lib/cmake/imgui/imguiTargets-debug.cmake"
		},
		{
			"isCMake" : true,
			"isExternal" : true,
			"path" : "/usr/share/cmake-3.29/Modules/CMakePackageConfigHelpers.cmake"
		},
		{
			"isCMake" : true,
			"isExternal" : true,
			"path" : "/usr/share/cmake-3.29/Modules/WriteBasicConfigVersionFile.cmake"
		},
		{
			"isCMake" : true,
			"isExternal" : true,
			"path" : "/usr/share/cmake-3.29/Modules/GNUInstallDirs.cmake"
		},
		{
			"isGenerated" : true,
			"path" : "build/_deps/packageproject.cmake-src/version.h.in"
		},
		{
			"isCMake" : true,
			"isExternal" : true,
			"path" : "/usr/share/cmake-3.29/Modules/BasicConfigVersion-AnyNewerVersion.cmake.in"
		},
		{
			"isGenerated" : true,
			"path" : "build/_deps/packageproject.cmake-src/Config.cmake.in"
		},
		{
			"isGenerated" : true,
			"path" : "build/_deps/packageproject.cmake-src/CMakeLists.txt"
		}
	],
	"kind" : "cmakeFiles",
	"paths" : 
	{
		"build" : "/home/deb/Downloads/CLCPP-Vulkan-Tools/build",
		"source" : "/home/deb/Downloads/CLCPP-Vulkan-Tools"
	},
	"version" : 
	{
		"major" : 1,
		"minor" : 0
	}
}
